gym_mapf/__init__.py
gym_mapf/envs/__init__.py
gym_mapf/envs/grid.py
gym_mapf/envs/mapf_env.py
gym_mapf/envs/utils.py
gym_mapf/maps/Berlin_1_256/Berlin_1_256-even-1.scen
gym_mapf/maps/Berlin_1_256/Berlin_1_256-even-10.scen
gym_mapf/maps/Berlin_1_256/Berlin_1_256-even-11.scen
gym_mapf/maps/Berlin_1_256/Berlin_1_256-even-12.scen
gym_mapf/maps/Berlin_1_256/Berlin_1_256-even-13.scen
gym_mapf/maps/Berlin_1_256/Berlin_1_256-even-14.scen
gym_mapf/maps/Berlin_1_256/Berlin_1_256-even-15.scen
gym_mapf/maps/Berlin_1_256/Berlin_1_256-even-16.scen
gym_mapf/maps/Berlin_1_256/Berlin_1_256-even-17.scen
gym_mapf/maps/Berlin_1_256/Berlin_1_256-even-18.scen
gym_mapf/maps/Berlin_1_256/Berlin_1_256-even-19.scen
gym_mapf/maps/Berlin_1_256/Berlin_1_256-even-2.scen
gym_mapf/maps/Berlin_1_256/Berlin_1_256-even-20.scen
gym_mapf/maps/Berlin_1_256/Berlin_1_256-even-21.scen
gym_mapf/maps/Berlin_1_256/Berlin_1_256-even-22.scen
gym_mapf/maps/Berlin_1_256/Berlin_1_256-even-23.scen
gym_mapf/maps/Berlin_1_256/Berlin_1_256-even-24.scen
gym_mapf/maps/Berlin_1_256/Berlin_1_256-even-25.scen
gym_mapf/maps/Berlin_1_256/Berlin_1_256-even-3.scen
gym_mapf/maps/Berlin_1_256/Berlin_1_256-even-4.scen
gym_mapf/maps/Berlin_1_256/Berlin_1_256-even-5.scen
gym_mapf/maps/Berlin_1_256/Berlin_1_256-even-6.scen
gym_mapf/maps/Berlin_1_256/Berlin_1_256-even-7.scen
gym_mapf/maps/Berlin_1_256/Berlin_1_256-even-8.scen
gym_mapf/maps/Berlin_1_256/Berlin_1_256-even-9.scen
gym_mapf/maps/Berlin_1_256/Berlin_1_256.map
gym_mapf/maps/empty-16-16/empty-16-16-even-1.scen
gym_mapf/maps/empty-16-16/empty-16-16-even-10.scen
gym_mapf/maps/empty-16-16/empty-16-16-even-11.scen
gym_mapf/maps/empty-16-16/empty-16-16-even-12.scen
gym_mapf/maps/empty-16-16/empty-16-16-even-13.scen
gym_mapf/maps/empty-16-16/empty-16-16-even-14.scen
gym_mapf/maps/empty-16-16/empty-16-16-even-15.scen
gym_mapf/maps/empty-16-16/empty-16-16-even-16.scen
gym_mapf/maps/empty-16-16/empty-16-16-even-17.scen
gym_mapf/maps/empty-16-16/empty-16-16-even-18.scen
gym_mapf-0.4.6.dist-info/LICENSE
gym_mapf-0.4.6.dist-info/METADATA
gym_mapf-0.4.6.dist-info/WHEEL
gym_mapf-0.4.6.dist-info/top_level.txt
gym_mapf-0.4.6.dist-info/RECORD
